nvimclient/__init__.py
nvimclient/__main__.py
nvimclient-0.1.3.dist-info/LICENSE
nvimclient-0.1.3.dist-info/METADATA
nvimclient-0.1.3.dist-info/WHEEL
nvimclient-0.1.3.dist-info/entry_points.txt
nvimclient-0.1.3.dist-info/top_level.txt
nvimclient-0.1.3.dist-info/RECORD
