Metadata-Version: 2.1
Name: nvimclient
Version: 0.1.3
Summary: Open new file in existing neovim instance, worked on both windows and linux, powered by pynvim.
Home-page: https://github.com/Verf/nvimclient
Author: Verf
Author-email: verf@protonmail.com
Classifier: License :: OSI Approved :: MIT License
Classifier: Programming Language :: Python :: 3
Classifier: Operating System :: OS Independent
Requires-Python: >=3.4
License-File: LICENSE
Requires-Dist: pynvim (>=0.4.3)
